setup.py
pyshowoff/__init__.py
tele/__init__.py
tele/meter.py
tele.egg-info/PKG-INFO
tele.egg-info/SOURCES.txt
tele.egg-info/dependency_links.txt
tele.egg-info/top_level.txt
tele/output/__init__.py
tele/output/console.py
tele/output/folder.py
tele/output/showoff.py