Metadata-Version: 1.0
Name: tele
Version: 0.0.0
Summary: Telemetry for PyTorch
Home-page: UNKNOWN
Author: Aiden Nibali
Author-email: UNKNOWN
License: UNKNOWN
Platform: UNKNOWN
